mcp_cli/__init__.py
mcp_cli/cli.py
mcp_cli/config.py
mcp_cli/commands/__init__.py
mcp_cli/commands/ask.py
mcp_cli/commands/servers.py
dschwartz_mcp_cli-0.1.0.dist-info/METADATA
dschwartz_mcp_cli-0.1.0.dist-info/WHEEL
dschwartz_mcp_cli-0.1.0.dist-info/entry_points.txt
dschwartz_mcp_cli-0.1.0.dist-info/top_level.txt
dschwartz_mcp_cli-0.1.0.dist-info/RECORD
