Metadata-Version: 2.4
Name: dschwartz-mcp-cli
Version: 0.1.0
Summary: A command-line interface for interacting with MCP servers
Author-email: Daniel Schwartz <dschwartz@example.com>
License: MIT
Project-URL: Homepage, https://github.com/yourusername/mcp-cli
Project-URL: Bug Tracker, https://github.com/yourusername/mcp-cli/issues
Classifier: Programming Language :: Python :: 3
Classifier: License :: OSI Approved :: MIT License
Classifier: Operating System :: OS Independent
Requires-Python: >=3.9
Requires-Dist: mcp>=1.6.0
